restart_datasets/__init__.py
restart_datasets/core.py
restart_datasets/dataset_info.json
restart_datasets/datasets.json
restart_datasets/local_datasets.json
restart_datasets/utils.py
restart_datasets/_data/Alabama.csv
restart_datasets/_data/Alaska.csv
restart_datasets/_data/Arizona.csv
restart_datasets/_data/Arkansas.csv
restart_datasets/_data/California.csv
restart_datasets/_data/Colorado.csv
restart_datasets/_data/Connecticut.csv
restart_datasets/_data/Delaware.csv
restart_datasets/_data/DistrictOfColumbia.csv
restart_datasets/_data/Florida.csv
restart_datasets/_data/Georgia.csv
restart_datasets/_data/Hawaii.csv
restart_datasets/_data/Idaho.csv
restart_datasets/_data/Illinois.csv
restart_datasets/_data/Indiana.csv
restart_datasets/_data/Iowa.csv
restart_datasets/_data/Kansas.csv
restart_datasets/_data/Kentucky.csv
restart_datasets/_data/Louisiana.csv
restart_datasets/_data/Maine.csv
restart_datasets/_data/Maryland.csv
restart_datasets/_data/Massachusetts.csv
restart_datasets/_data/Michigan.csv
restart_datasets/_data/Minnesota.csv
restart_datasets/_data/Mississippi.csv
restart_datasets/_data/Missouri.csv
restart_datasets/_data/Montana.csv
restart_datasets/_data/Nebraska.csv
restart_datasets/_data/Nevada.csv
restart_datasets/_data/NewHampshire.csv
restart_datasets/_data/NewJersey.csv
restart_datasets/_data/NewMexico.csv
restart_datasets/_data/NewYork.csv
restart_datasets/_data/NorthCarolina.csv
restart_datasets/_data/NorthDakota.csv
restart_datasets/_data/Ohio.csv
restart_datasets/_data/Oklahoma.csv
restart_datasets/_data/Oregon.csv
restart_datasets/_data/Pennsylvania.csv
restart_datasets/_data/RhodeIsland.csv
restart_datasets/_data/SouthCarolina.csv
restart_datasets/_data/SouthDakota.csv
restart_datasets/_data/Tennessee.csv
restart_datasets/_data/Texas.csv
restart_datasets/_data/Utah.csv
restart_datasets/_data/Vermont.csv
restart_datasets/_data/Virginia.csv
restart_datasets/_data/Washington.csv
restart_datasets/_data/WestVirginia.csv
restart_datasets-0.6.dist-info/LICENSE
restart_datasets-0.6.dist-info/METADATA
restart_datasets-0.6.dist-info/WHEEL
restart_datasets-0.6.dist-info/top_level.txt
restart_datasets-0.6.dist-info/RECORD
