Metadata-Version: 2.1
Name: restart-datasets
Version: 0.6
Summary: Python package for offline access to restart datasets
Home-page: http://github.com/restartus/restart_datasets
Author: Restart Partners
Author-email: info@restart.us
Maintainer: Lucas Hahn
Maintainer-email: lucas@restart.us
License: UNKNOWN
Platform: UNKNOWN
Classifier: Environment :: Console
Classifier: Intended Audience :: Science/Research
Classifier: Programming Language :: Python :: 3.8
Requires-Python: >=3.8
Requires-Dist: pandas
